setup.py
tikteck/__init__.py
tikteck.egg-info/PKG-INFO
tikteck.egg-info/SOURCES.txt
tikteck.egg-info/dependency_links.txt
tikteck.egg-info/not-zip-safe
tikteck.egg-info/top_level.txt