Metadata-Version: 1.1
Name: tikteck
Version: 0.3
Summary: Python API for controlling Tikteck LED bulbs
Home-page: http://github.com/mjg59/python-tikteck
Author: Matthew Garrett
Author-email: mjg59@srcf.ucam.org
License: UNKNOWN
Platform: UNKNOWN
Classifier: Development Status :: 4 - Beta
Classifier: Intended Audience :: Developers
Classifier: License :: OSI Approved :: MIT License
Classifier: Operating System :: OS Independent
Classifier: Programming Language :: Python
